pubtools/_ami/__init__.py
pubtools/_ami/arguments.py
pubtools/_ami/rhsm.py
pubtools/_ami/step.py
pubtools/_ami/task.py
pubtools/_ami/services/__init__.py
pubtools/_ami/services/aws.py
pubtools/_ami/services/base.py
pubtools/_ami/services/collector.py
pubtools/_ami/services/rhsm_.py
pubtools/_ami/tasks/__init__.py
pubtools/_ami/tasks/base.py
pubtools/_ami/tasks/delete.py
pubtools/_ami/tasks/exceptions.py
pubtools/_ami/tasks/push.py
pubtools_ami-2.4.2.dist-info/LICENSE
pubtools_ami-2.4.2.dist-info/METADATA
pubtools_ami-2.4.2.dist-info/WHEEL
pubtools_ami-2.4.2.dist-info/entry_points.txt
pubtools_ami-2.4.2.dist-info/top_level.txt
pubtools_ami-2.4.2.dist-info/RECORD
