Metadata-Version: 2.1
Name: pubtools-ami
Version: 2.4.2
Summary: Publishing tools for Amazon machine Images(AMI)
Home-page: https://github.com/release-engineering/pubtools-ami
License: GNU General Public License
Project-URL: Documentation, https://release-engineering.github.io/pubtools-ami/
Project-URL: Changelog, https://github.com/release-engineering/pubtools-ami/blob/master/CHANGELOG.md
Classifier: Development Status :: 4 - Beta
Classifier: Intended Audience :: Developers
Classifier: License :: OSI Approved :: GNU General Public License v3 or later (GPLv3+)
Classifier: Programming Language :: Python :: 3
Classifier: Topic :: Software Development :: Libraries :: Python Modules
Requires-Python: >=3.6
License-File: LICENSE
Requires-Dist: more-executors
Requires-Dist: pushsource >=2.39.0
Requires-Dist: pushcollector
Requires-Dist: cloudimg >=1.8.0
Requires-Dist: attrs
Requires-Dist: pubtools
